{"slug":"a-u-s-a","marca":"A.U.S.A.","total_hist":4752,"parque_activo":0,"dominio":"mixto","tiene_ev":false,"pocos_datos":true,"ultimo_periodo":"2026-03","generado_en":"2026-04-23","stats":{"parque_activo":0,"matric_ytd":0,"matric_ytd_prev":0,"cuota_bevphev_ytd_pct":0,"cuota_mercado_ytd_pct":0,"cuota_mercado_ytd_prev_pct":0,"ranking_ytd":null,"ranking_ytd_prev":null,"edad_media_parque":0,"ratio_bajas_matric_ytd":0},"serie_mensual":[{"periodo":"2014-12","bev":0,"phev":0,"hev":0,"otro":0,"bajas":183},{"periodo":"2015-01","bev":0,"phev":0,"hev":0,"otro":0,"bajas":52},{"periodo":"2015-02","bev":0,"phev":0,"hev":0,"otro":0,"bajas":76},{"periodo":"2015-03","bev":0,"phev":0,"hev":0,"otro":0,"bajas":138},{"periodo":"2015-04","bev":0,"phev":0,"hev":0,"otro":0,"bajas":69},{"periodo":"2015-05","bev":0,"phev":0,"hev":0,"otro":0,"bajas":78},{"periodo":"2015-06","bev":0,"phev":0,"hev":0,"otro":0,"bajas":151},{"periodo":"2015-07","bev":0,"phev":0,"hev":0,"otro":0,"bajas":45},{"periodo":"2015-08","bev":0,"phev":0,"hev":0,"otro":0,"bajas":29},{"periodo":"2015-09","bev":0,"phev":0,"hev":0,"otro":0,"bajas":104},{"periodo":"2015-10","bev":0,"phev":0,"hev":0,"otro":0,"bajas":117},{"periodo":"2015-11","bev":0,"phev":0,"hev":0,"otro":0,"bajas":79},{"periodo":"2015-12","bev":0,"phev":0,"hev":0,"otro":0,"bajas":126},{"periodo":"2016-01","bev":0,"phev":0,"hev":0,"otro":42,"bajas":51},{"periodo":"2016-02","bev":0,"phev":0,"hev":0,"otro":37,"bajas":39},{"periodo":"2016-03","bev":0,"phev":0,"hev":0,"otro":57,"bajas":109},{"periodo":"2016-04","bev":0,"phev":0,"hev":0,"otro":52,"bajas":92},{"periodo":"2016-05","bev":0,"phev":0,"hev":0,"otro":30,"bajas":68},{"periodo":"2016-06","bev":0,"phev":0,"hev":0,"otro":33,"bajas":65},{"periodo":"2016-07","bev":0,"phev":0,"hev":0,"otro":32,"bajas":42},{"periodo":"2016-08","bev":0,"phev":0,"hev":0,"otro":14,"bajas":27},{"periodo":"2016-09","bev":0,"phev":0,"hev":0,"otro":31,"bajas":65},{"periodo":"2016-10","bev":0,"phev":0,"hev":0,"otro":25,"bajas":39},{"periodo":"2016-11","bev":0,"phev":0,"hev":0,"otro":32,"bajas":95},{"periodo":"2016-12","bev":0,"phev":0,"hev":0,"otro":44,"bajas":131},{"periodo":"2017-01","bev":0,"phev":0,"hev":0,"otro":48,"bajas":62},{"periodo":"2017-02","bev":0,"phev":0,"hev":0,"otro":63,"bajas":61},{"periodo":"2017-03","bev":0,"phev":0,"hev":0,"otro":70,"bajas":98},{"periodo":"2017-04","bev":0,"phev":0,"hev":0,"otro":56,"bajas":60},{"periodo":"2017-05","bev":0,"phev":0,"hev":0,"otro":95,"bajas":95},{"periodo":"2017-06","bev":0,"phev":0,"hev":0,"otro":60,"bajas":87},{"periodo":"2017-07","bev":0,"phev":0,"hev":0,"otro":80,"bajas":45},{"periodo":"2017-08","bev":0,"phev":0,"hev":0,"otro":72,"bajas":32},{"periodo":"2017-09","bev":0,"phev":0,"hev":0,"otro":37,"bajas":47},{"periodo":"2017-10","bev":0,"phev":0,"hev":0,"otro":55,"bajas":60},{"periodo":"2017-11","bev":0,"phev":0,"hev":0,"otro":62,"bajas":60},{"periodo":"2017-12","bev":0,"phev":0,"hev":0,"otro":46,"bajas":110},{"periodo":"2018-01","bev":0,"phev":0,"hev":0,"otro":63,"bajas":46},{"periodo":"2018-02","bev":0,"phev":0,"hev":0,"otro":95,"bajas":77},{"periodo":"2018-03","bev":0,"phev":0,"hev":0,"otro":117,"bajas":64},{"periodo":"2018-04","bev":0,"phev":0,"hev":0,"otro":156,"bajas":43},{"periodo":"2018-05","bev":0,"phev":0,"hev":0,"otro":107,"bajas":45},{"periodo":"2018-06","bev":0,"phev":0,"hev":0,"otro":90,"bajas":59},{"periodo":"2018-07","bev":0,"phev":0,"hev":0,"otro":92,"bajas":48},{"periodo":"2018-08","bev":0,"phev":0,"hev":0,"otro":35,"bajas":28},{"periodo":"2018-09","bev":0,"phev":0,"hev":0,"otro":44,"bajas":60},{"periodo":"2018-10","bev":0,"phev":0,"hev":0,"otro":89,"bajas":63},{"periodo":"2018-11","bev":0,"phev":0,"hev":0,"otro":91,"bajas":89},{"periodo":"2018-12","bev":0,"phev":0,"hev":0,"otro":53,"bajas":104},{"periodo":"2019-01","bev":0,"phev":0,"hev":0,"otro":109,"bajas":56},{"periodo":"2019-02","bev":0,"phev":0,"hev":0,"otro":154,"bajas":50},{"periodo":"2019-03","bev":0,"phev":0,"hev":0,"otro":160,"bajas":51},{"periodo":"2019-04","bev":0,"phev":0,"hev":0,"otro":138,"bajas":43},{"periodo":"2019-05","bev":0,"phev":0,"hev":0,"otro":121,"bajas":95},{"periodo":"2019-06","bev":0,"phev":0,"hev":0,"otro":115,"bajas":51},{"periodo":"2019-07","bev":0,"phev":0,"hev":0,"otro":96,"bajas":34},{"periodo":"2019-08","bev":0,"phev":0,"hev":0,"otro":41,"bajas":29},{"periodo":"2019-09","bev":0,"phev":0,"hev":0,"otro":59,"bajas":53},{"periodo":"2019-10","bev":0,"phev":0,"hev":0,"otro":58,"bajas":65},{"periodo":"2019-11","bev":0,"phev":0,"hev":0,"otro":78,"bajas":76},{"periodo":"2019-12","bev":0,"phev":0,"hev":0,"otro":59,"bajas":71},{"periodo":"2020-01","bev":0,"phev":0,"hev":0,"otro":45,"bajas":48},{"periodo":"2020-02","bev":0,"phev":0,"hev":0,"otro":107,"bajas":56},{"periodo":"2020-03","bev":0,"phev":0,"hev":0,"otro":43,"bajas":58},{"periodo":"2020-04","bev":0,"phev":0,"hev":0,"otro":36,"bajas":33},{"periodo":"2020-05","bev":0,"phev":0,"hev":0,"otro":78,"bajas":24},{"periodo":"2020-06","bev":0,"phev":0,"hev":0,"otro":119,"bajas":20},{"periodo":"2020-07","bev":0,"phev":0,"hev":0,"otro":95,"bajas":49},{"periodo":"2020-08","bev":0,"phev":0,"hev":0,"otro":39,"bajas":42},{"periodo":"2020-09","bev":0,"phev":0,"hev":0,"otro":43,"bajas":52},{"periodo":"2020-10","bev":0,"phev":0,"hev":0,"otro":52,"bajas":70},{"periodo":"2020-11","bev":0,"phev":0,"hev":0,"otro":62,"bajas":65},{"periodo":"2020-12","bev":0,"phev":0,"hev":0,"otro":63,"bajas":108},{"periodo":"2021-01","bev":0,"phev":0,"hev":0,"otro":63,"bajas":45},{"periodo":"2021-02","bev":0,"phev":0,"hev":0,"otro":78,"bajas":34},{"periodo":"2021-03","bev":0,"phev":0,"hev":0,"otro":90,"bajas":75},{"periodo":"2021-04","bev":0,"phev":0,"hev":0,"otro":90,"bajas":54},{"periodo":"2021-05","bev":0,"phev":0,"hev":0,"otro":104,"bajas":65},{"periodo":"2021-06","bev":0,"phev":0,"hev":0,"otro":65,"bajas":69},{"periodo":"2021-07","bev":0,"phev":0,"hev":0,"otro":87,"bajas":64}],"mix_tipo_grupo":{},"top_modelos_parque":[],"mix_tecnologia_anual":[{"año":2014,"bev":0,"phev":0,"hev":0,"otro":0},{"año":2015,"bev":0,"phev":0,"hev":0,"otro":0},{"año":2016,"bev":0,"phev":0,"hev":0,"otro":429},{"año":2017,"bev":0,"phev":0,"hev":0,"otro":744},{"año":2018,"bev":0,"phev":0,"hev":0,"otro":1032},{"año":2019,"bev":0,"phev":0,"hev":0,"otro":1188},{"año":2020,"bev":0,"phev":0,"hev":0,"otro":782},{"año":2021,"bev":0,"phev":0,"hev":0,"otro":577}],"por_provincia":{},"sociologia":{"persona":{},"renting":{"S":0,"N":0},"servicio":{}},"distintivo_ambiental":{"CERO":0,"ECO":0,"C":0,"B":0,"SIN":0},"piramide_edad":[],"radar_vs_mercado":{"co2_marca":null,"kw_marca":null,"peso_marca":null,"autonomia_bev_km_marca":null,"n_muestra_marca":0,"co2_mercado":117.6,"kw_mercado":100.8,"peso_mercado":1505,"autonomia_bev_km_mercado":467},"bajas_por_motivo":{"3":1066,"6":3419,"7":832,"8":0,"otros":1},"cohortes":[{"año":2016,"matriculadas":429,"activas_hoy":0},{"año":2017,"matriculadas":744,"activas_hoy":0},{"año":2018,"matriculadas":1030,"activas_hoy":0},{"año":2019,"matriculadas":1173,"activas_hoy":0},{"año":2020,"matriculadas":774,"activas_hoy":0},{"año":2021,"matriculadas":574,"activas_hoy":0}]}