{"slug":"electric-motion","marca":"ELECTRIC MOTION","total_hist":246,"parque_activo":87,"dominio":"moto","tiene_ev":true,"pocos_datos":true,"ultimo_periodo":"2026-03","generado_en":"2026-04-23","stats":{"parque_activo":87,"matric_ytd":7,"matric_ytd_prev":9,"cuota_bevphev_ytd_pct":0,"cuota_mercado_ytd_pct":0.001,"cuota_mercado_ytd_prev_pct":0.002,"ranking_ytd":705,"ranking_ytd_prev":592,"edad_media_parque":3.4,"ratio_bajas_matric_ytd":14.29},"serie_mensual":[{"periodo":"2016-11","bev":0,"phev":0,"hev":0,"otro":1,"bajas":0},{"periodo":"2017-11","bev":0,"phev":0,"hev":0,"otro":1,"bajas":0},{"periodo":"2018-12","bev":0,"phev":0,"hev":0,"otro":1,"bajas":0},{"periodo":"2019-01","bev":0,"phev":0,"hev":1,"otro":9,"bajas":0},{"periodo":"2019-03","bev":0,"phev":0,"hev":0,"otro":1,"bajas":0},{"periodo":"2019-05","bev":0,"phev":0,"hev":0,"otro":1,"bajas":1},{"periodo":"2019-06","bev":0,"phev":0,"hev":0,"otro":2,"bajas":0},{"periodo":"2019-10","bev":0,"phev":0,"hev":0,"otro":3,"bajas":1},{"periodo":"2019-11","bev":0,"phev":0,"hev":0,"otro":1,"bajas":0},{"periodo":"2019-12","bev":0,"phev":0,"hev":0,"otro":3,"bajas":4},{"periodo":"2020-01","bev":0,"phev":0,"hev":0,"otro":4,"bajas":0},{"periodo":"2020-02","bev":0,"phev":0,"hev":0,"otro":2,"bajas":0},{"periodo":"2020-03","bev":0,"phev":0,"hev":0,"otro":1,"bajas":0},{"periodo":"2020-04","bev":0,"phev":0,"hev":0,"otro":2,"bajas":0},{"periodo":"2020-05","bev":0,"phev":0,"hev":0,"otro":2,"bajas":0},{"periodo":"2020-06","bev":0,"phev":0,"hev":0,"otro":1,"bajas":0},{"periodo":"2020-07","bev":0,"phev":0,"hev":0,"otro":3,"bajas":0},{"periodo":"2020-09","bev":0,"phev":0,"hev":0,"otro":2,"bajas":0},{"periodo":"2020-10","bev":0,"phev":0,"hev":0,"otro":2,"bajas":0},{"periodo":"2020-11","bev":0,"phev":0,"hev":0,"otro":7,"bajas":0},{"periodo":"2020-12","bev":0,"phev":0,"hev":0,"otro":6,"bajas":0},{"periodo":"2021-01","bev":0,"phev":0,"hev":0,"otro":3,"bajas":0},{"periodo":"2021-02","bev":0,"phev":0,"hev":0,"otro":2,"bajas":0},{"periodo":"2021-03","bev":0,"phev":0,"hev":0,"otro":2,"bajas":1},{"periodo":"2021-04","bev":0,"phev":0,"hev":0,"otro":4,"bajas":0},{"periodo":"2021-05","bev":0,"phev":0,"hev":0,"otro":3,"bajas":0},{"periodo":"2021-06","bev":0,"phev":0,"hev":0,"otro":5,"bajas":0},{"periodo":"2021-07","bev":0,"phev":0,"hev":0,"otro":0,"bajas":1},{"periodo":"2021-09","bev":0,"phev":0,"hev":0,"otro":3,"bajas":0},{"periodo":"2021-10","bev":0,"phev":0,"hev":0,"otro":3,"bajas":0},{"periodo":"2021-11","bev":0,"phev":0,"hev":0,"otro":1,"bajas":1},{"periodo":"2021-12","bev":0,"phev":0,"hev":0,"otro":3,"bajas":0},{"periodo":"2022-02","bev":0,"phev":0,"hev":0,"otro":5,"bajas":0},{"periodo":"2022-03","bev":0,"phev":0,"hev":0,"otro":4,"bajas":0},{"periodo":"2022-04","bev":0,"phev":0,"hev":0,"otro":5,"bajas":0},{"periodo":"2022-05","bev":0,"phev":0,"hev":0,"otro":2,"bajas":0},{"periodo":"2022-06","bev":0,"phev":0,"hev":0,"otro":1,"bajas":0},{"periodo":"2022-07","bev":0,"phev":0,"hev":0,"otro":6,"bajas":0},{"periodo":"2022-08","bev":0,"phev":0,"hev":0,"otro":6,"bajas":0},{"periodo":"2022-09","bev":0,"phev":0,"hev":0,"otro":9,"bajas":0},{"periodo":"2022-11","bev":0,"phev":0,"hev":0,"otro":1,"bajas":1},{"periodo":"2022-12","bev":0,"phev":0,"hev":0,"otro":4,"bajas":0},{"periodo":"2023-01","bev":0,"phev":0,"hev":0,"otro":1,"bajas":0},{"periodo":"2023-02","bev":0,"phev":0,"hev":0,"otro":1,"bajas":0},{"periodo":"2023-03","bev":0,"phev":0,"hev":0,"otro":4,"bajas":0},{"periodo":"2023-04","bev":0,"phev":0,"hev":0,"otro":1,"bajas":1},{"periodo":"2023-05","bev":0,"phev":0,"hev":0,"otro":10,"bajas":0},{"periodo":"2023-06","bev":0,"phev":0,"hev":0,"otro":3,"bajas":0},{"periodo":"2023-07","bev":0,"phev":0,"hev":0,"otro":1,"bajas":0},{"periodo":"2023-08","bev":0,"phev":0,"hev":0,"otro":0,"bajas":1},{"periodo":"2023-10","bev":0,"phev":0,"hev":0,"otro":1,"bajas":0},{"periodo":"2023-11","bev":0,"phev":0,"hev":0,"otro":3,"bajas":2},{"periodo":"2023-12","bev":0,"phev":0,"hev":0,"otro":2,"bajas":0},{"periodo":"2024-01","bev":1,"phev":0,"hev":0,"otro":10,"bajas":1},{"periodo":"2024-02","bev":0,"phev":0,"hev":0,"otro":3,"bajas":1},{"periodo":"2024-03","bev":0,"phev":0,"hev":0,"otro":2,"bajas":3},{"periodo":"2024-04","bev":0,"phev":0,"hev":0,"otro":3,"bajas":0},{"periodo":"2024-05","bev":0,"phev":0,"hev":0,"otro":6,"bajas":0},{"periodo":"2024-06","bev":0,"phev":0,"hev":0,"otro":2,"bajas":0},{"periodo":"2024-07","bev":0,"phev":0,"hev":0,"otro":8,"bajas":0},{"periodo":"2024-08","bev":0,"phev":0,"hev":0,"otro":5,"bajas":1},{"periodo":"2024-09","bev":0,"phev":0,"hev":0,"otro":2,"bajas":0},{"periodo":"2024-10","bev":0,"phev":0,"hev":0,"otro":3,"bajas":1},{"periodo":"2024-11","bev":0,"phev":0,"hev":0,"otro":4,"bajas":0},{"periodo":"2024-12","bev":0,"phev":0,"hev":0,"otro":8,"bajas":0},{"periodo":"2025-01","bev":0,"phev":0,"hev":0,"otro":2,"bajas":0},{"periodo":"2025-02","bev":0,"phev":0,"hev":0,"otro":4,"bajas":2},{"periodo":"2025-03","bev":0,"phev":0,"hev":0,"otro":3,"bajas":0},{"periodo":"2025-04","bev":0,"phev":0,"hev":0,"otro":3,"bajas":0},{"periodo":"2025-05","bev":0,"phev":0,"hev":0,"otro":2,"bajas":1},{"periodo":"2025-06","bev":0,"phev":0,"hev":0,"otro":5,"bajas":1},{"periodo":"2025-07","bev":0,"phev":0,"hev":0,"otro":1,"bajas":0},{"periodo":"2025-08","bev":0,"phev":0,"hev":0,"otro":2,"bajas":0},{"periodo":"2025-09","bev":0,"phev":0,"hev":0,"otro":1,"bajas":1},{"periodo":"2025-10","bev":0,"phev":0,"hev":0,"otro":0,"bajas":1},{"periodo":"2025-11","bev":0,"phev":0,"hev":0,"otro":2,"bajas":0},{"periodo":"2025-12","bev":0,"phev":0,"hev":0,"otro":2,"bajas":1},{"periodo":"2026-01","bev":0,"phev":0,"hev":0,"otro":2,"bajas":0},{"periodo":"2026-02","bev":0,"phev":0,"hev":0,"otro":4,"bajas":0},{"periodo":"2026-03","bev":0,"phev":0,"hev":0,"otro":1,"bajas":1}],"mix_tipo_grupo":{"moto":{"total":87,"bev":0,"phev":0,"hev":1,"no_enchufable":87}},"top_modelos_parque":[{"modelo":"TEM","tipo_grupo":"moto","total":79,"bev":0,"phev":0,"hev":0,"no_ev":79}],"mix_tecnologia_anual":[{"año":2016,"bev":0,"phev":0,"hev":0,"otro":1},{"año":2017,"bev":0,"phev":0,"hev":0,"otro":1},{"año":2018,"bev":0,"phev":0,"hev":0,"otro":1},{"año":2019,"bev":0,"phev":0,"hev":1,"otro":20},{"año":2020,"bev":0,"phev":0,"hev":0,"otro":32},{"año":2021,"bev":0,"phev":0,"hev":0,"otro":29},{"año":2022,"bev":0,"phev":0,"hev":0,"otro":43},{"año":2023,"bev":0,"phev":0,"hev":0,"otro":27},{"año":2024,"bev":1,"phev":0,"hev":0,"otro":56},{"año":2025,"bev":0,"phev":0,"hev":0,"otro":27},{"año":2026,"bev":0,"phev":0,"hev":0,"otro":7}],"por_provincia":{"24":{"parque":29,"cuota_pct":0.007,"ranking":189,"top_3":["TEM"]},"25":{"parque":7,"cuota_pct":0.002,"ranking":382,"top_3":["TEM"]},"28":{"parque":35,"cuota_pct":0.001,"ranking":538,"top_3":["TEM"]},"08":{"parque":16,"cuota_pct":0,"ranking":638,"top_3":["TEM"]}},"sociologia":{"persona":{"D":62,"X":13},"renting":{"S":0,"N":75},"servicio":{"B00":75}},"distintivo_ambiental":{"CERO":87,"ECO":0,"C":0,"B":0,"SIN":0},"piramide_edad":[{"años":0,"bev":0,"phev":0,"hev":0,"no_ev":3},{"años":1,"bev":0,"phev":0,"hev":0,"no_ev":9},{"años":2,"bev":0,"phev":0,"hev":0,"no_ev":24},{"años":3,"bev":0,"phev":0,"hev":0,"no_ev":10},{"años":4,"bev":0,"phev":0,"hev":0,"no_ev":19},{"años":5,"bev":0,"phev":0,"hev":0,"no_ev":7},{"años":6,"bev":0,"phev":0,"hev":0,"no_ev":10},{"años":7,"bev":0,"phev":0,"hev":1,"no_ev":4}],"radar_vs_mercado":{"co2_marca":null,"kw_marca":null,"peso_marca":null,"autonomia_bev_km_marca":null,"n_muestra_marca":0,"co2_mercado":117.6,"kw_mercado":100.8,"peso_mercado":1505,"autonomia_bev_km_mercado":467}}