{"slug":"suzuki","marca":"SUZUKI","total_hist":127162,"parque_activo":679704,"dominio":"mixto","tiene_ev":true,"pocos_datos":false,"ultimo_periodo":"2026-03","generado_en":"2026-04-23","stats":{"parque_activo":679704,"matric_ytd":2702,"matric_ytd_prev":2626,"cuota_bevphev_ytd_pct":0.56,"cuota_mercado_ytd_pct":0.538,"cuota_mercado_ytd_prev_pct":0.581,"ranking_ytd":33,"ranking_ytd_prev":29,"edad_media_parque":20.8,"ratio_bajas_matric_ytd":176.65},"serie_mensual":[{"periodo":"2014-12","bev":0,"phev":0,"hev":0,"otro":648,"bajas":3626},{"periodo":"2015-01","bev":0,"phev":0,"hev":0,"otro":575,"bajas":1162},{"periodo":"2015-02","bev":0,"phev":0,"hev":0,"otro":656,"bajas":1498},{"periodo":"2015-03","bev":0,"phev":0,"hev":0,"otro":943,"bajas":1801},{"periodo":"2015-04","bev":0,"phev":0,"hev":0,"otro":1165,"bajas":1668},{"periodo":"2015-05","bev":0,"phev":0,"hev":0,"otro":1271,"bajas":1703},{"periodo":"2015-06","bev":0,"phev":0,"hev":0,"otro":1470,"bajas":1790},{"periodo":"2015-07","bev":0,"phev":0,"hev":0,"otro":1428,"bajas":1703},{"periodo":"2015-08","bev":0,"phev":0,"hev":0,"otro":921,"bajas":1357},{"periodo":"2015-09","bev":0,"phev":0,"hev":0,"otro":1552,"bajas":1576},{"periodo":"2015-10","bev":0,"phev":0,"hev":0,"otro":923,"bajas":1759},{"periodo":"2015-11","bev":0,"phev":0,"hev":0,"otro":872,"bajas":1761},{"periodo":"2015-12","bev":0,"phev":0,"hev":0,"otro":791,"bajas":3327},{"periodo":"2016-01","bev":0,"phev":0,"hev":0,"otro":820,"bajas":1640},{"periodo":"2016-02","bev":0,"phev":0,"hev":0,"otro":966,"bajas":1579},{"periodo":"2016-03","bev":0,"phev":0,"hev":0,"otro":1007,"bajas":1800},{"periodo":"2016-04","bev":0,"phev":0,"hev":0,"otro":1151,"bajas":1884},{"periodo":"2016-05","bev":0,"phev":0,"hev":0,"otro":1324,"bajas":1918},{"periodo":"2016-06","bev":0,"phev":0,"hev":0,"otro":1792,"bajas":1869},{"periodo":"2016-07","bev":0,"phev":0,"hev":0,"otro":1417,"bajas":1665},{"periodo":"2016-08","bev":0,"phev":0,"hev":0,"otro":983,"bajas":1615},{"periodo":"2016-09","bev":0,"phev":0,"hev":0,"otro":1199,"bajas":1694},{"periodo":"2016-10","bev":0,"phev":0,"hev":0,"otro":928,"bajas":1704},{"periodo":"2016-11","bev":0,"phev":0,"hev":0,"otro":1054,"bajas":1973},{"periodo":"2016-12","bev":0,"phev":0,"hev":0,"otro":1587,"bajas":2990},{"periodo":"2017-01","bev":0,"phev":0,"hev":0,"otro":703,"bajas":1630},{"periodo":"2017-02","bev":0,"phev":0,"hev":11,"otro":854,"bajas":1561},{"periodo":"2017-03","bev":0,"phev":0,"hev":21,"otro":1356,"bajas":1840},{"periodo":"2017-04","bev":0,"phev":0,"hev":11,"otro":885,"bajas":1605},{"periodo":"2017-05","bev":0,"phev":0,"hev":25,"otro":1087,"bajas":1915},{"periodo":"2017-06","bev":0,"phev":0,"hev":33,"otro":1321,"bajas":1770},{"periodo":"2017-07","bev":0,"phev":0,"hev":31,"otro":1112,"bajas":1609},{"periodo":"2017-08","bev":0,"phev":0,"hev":24,"otro":868,"bajas":1387},{"periodo":"2017-09","bev":0,"phev":0,"hev":20,"otro":1225,"bajas":1615},{"periodo":"2017-10","bev":0,"phev":0,"hev":12,"otro":1059,"bajas":1706},{"periodo":"2017-11","bev":0,"phev":0,"hev":26,"otro":1271,"bajas":1900},{"periodo":"2017-12","bev":0,"phev":0,"hev":35,"otro":1151,"bajas":2872},{"periodo":"2018-01","bev":0,"phev":0,"hev":41,"otro":993,"bajas":1642},{"periodo":"2018-02","bev":0,"phev":0,"hev":34,"otro":1097,"bajas":1595},{"periodo":"2018-03","bev":0,"phev":0,"hev":23,"otro":1216,"bajas":1646},{"periodo":"2018-04","bev":0,"phev":0,"hev":23,"otro":991,"bajas":1689},{"periodo":"2018-05","bev":0,"phev":0,"hev":56,"otro":1512,"bajas":1964},{"periodo":"2018-06","bev":0,"phev":0,"hev":55,"otro":1486,"bajas":1754},{"periodo":"2018-07","bev":0,"phev":0,"hev":29,"otro":1019,"bajas":1756},{"periodo":"2018-08","bev":0,"phev":0,"hev":38,"otro":988,"bajas":1507},{"periodo":"2018-09","bev":0,"phev":0,"hev":34,"otro":949,"bajas":1669},{"periodo":"2018-10","bev":0,"phev":0,"hev":47,"otro":937,"bajas":1982},{"periodo":"2018-11","bev":0,"phev":0,"hev":43,"otro":942,"bajas":2020},{"periodo":"2018-12","bev":0,"phev":0,"hev":45,"otro":1197,"bajas":2965},{"periodo":"2019-01","bev":0,"phev":0,"hev":42,"otro":873,"bajas":1698},{"periodo":"2019-02","bev":0,"phev":0,"hev":41,"otro":928,"bajas":1552},{"periodo":"2019-03","bev":0,"phev":0,"hev":36,"otro":1510,"bajas":1609},{"periodo":"2019-04","bev":0,"phev":0,"hev":37,"otro":1177,"bajas":1644},{"periodo":"2019-05","bev":0,"phev":0,"hev":42,"otro":1272,"bajas":1942},{"periodo":"2019-06","bev":0,"phev":0,"hev":38,"otro":1836,"bajas":1671},{"periodo":"2019-07","bev":0,"phev":0,"hev":34,"otro":1470,"bajas":2053},{"periodo":"2019-08","bev":0,"phev":0,"hev":30,"otro":1174,"bajas":1592},{"periodo":"2019-09","bev":0,"phev":0,"hev":78,"otro":964,"bajas":1728},{"periodo":"2019-10","bev":0,"phev":0,"hev":76,"otro":911,"bajas":2152},{"periodo":"2019-11","bev":0,"phev":0,"hev":103,"otro":816,"bajas":2015},{"periodo":"2019-12","bev":0,"phev":0,"hev":149,"otro":1229,"bajas":3179},{"periodo":"2020-01","bev":0,"phev":0,"hev":131,"otro":607,"bajas":1841},{"periodo":"2020-02","bev":0,"phev":0,"hev":189,"otro":640,"bajas":1755},{"periodo":"2020-03","bev":0,"phev":0,"hev":130,"otro":314,"bajas":1084},{"periodo":"2020-04","bev":0,"phev":0,"hev":1,"otro":28,"bajas":217},{"periodo":"2020-05","bev":0,"phev":0,"hev":61,"otro":327,"bajas":665},{"periodo":"2020-06","bev":0,"phev":0,"hev":363,"otro":691,"bajas":1608},{"periodo":"2020-07","bev":0,"phev":0,"hev":408,"otro":784,"bajas":1854},{"periodo":"2020-08","bev":0,"phev":0,"hev":360,"otro":484,"bajas":1570},{"periodo":"2020-09","bev":0,"phev":11,"hev":480,"otro":608,"bajas":1993},{"periodo":"2020-10","bev":0,"phev":6,"hev":368,"otro":385,"bajas":1957},{"periodo":"2020-11","bev":0,"phev":4,"hev":372,"otro":329,"bajas":1992},{"periodo":"2020-12","bev":0,"phev":59,"hev":527,"otro":356,"bajas":3273},{"periodo":"2021-01","bev":0,"phev":0,"hev":210,"otro":187,"bajas":1410},{"periodo":"2021-02","bev":0,"phev":0,"hev":319,"otro":255,"bajas":1406},{"periodo":"2021-03","bev":0,"phev":0,"hev":490,"otro":421,"bajas":1844},{"periodo":"2021-04","bev":0,"phev":0,"hev":307,"otro":318,"bajas":1771},{"periodo":"2021-05","bev":0,"phev":1,"hev":564,"otro":354,"bajas":1874},{"periodo":"2021-06","bev":0,"phev":2,"hev":615,"otro":369,"bajas":2045},{"periodo":"2021-07","bev":0,"phev":0,"hev":574,"otro":338,"bajas":1785},{"periodo":"2021-08","bev":0,"phev":0,"hev":328,"otro":223,"bajas":1472},{"periodo":"2021-09","bev":0,"phev":0,"hev":383,"otro":321,"bajas":1891},{"periodo":"2021-10","bev":0,"phev":8,"hev":408,"otro":240,"bajas":1831},{"periodo":"2021-11","bev":0,"phev":5,"hev":275,"otro":297,"bajas":2105},{"periodo":"2021-12","bev":0,"phev":14,"hev":561,"otro":315,"bajas":3393},{"periodo":"2022-01","bev":0,"phev":0,"hev":145,"otro":196,"bajas":1420},{"periodo":"2022-02","bev":0,"phev":1,"hev":171,"otro":221,"bajas":1684},{"periodo":"2022-03","bev":0,"phev":1,"hev":226,"otro":282,"bajas":1913},{"periodo":"2022-04","bev":0,"phev":2,"hev":209,"otro":224,"bajas":1541},{"periodo":"2022-05","bev":0,"phev":1,"hev":437,"otro":288,"bajas":1788},{"periodo":"2022-06","bev":0,"phev":1,"hev":384,"otro":324,"bajas":1600},{"periodo":"2022-07","bev":0,"phev":5,"hev":331,"otro":341,"bajas":1484},{"periodo":"2022-08","bev":0,"phev":3,"hev":306,"otro":265,"bajas":1388},{"periodo":"2022-09","bev":0,"phev":2,"hev":348,"otro":326,"bajas":1709},{"periodo":"2022-10","bev":0,"phev":5,"hev":379,"otro":257,"bajas":1749},{"periodo":"2022-11","bev":0,"phev":1,"hev":269,"otro":278,"bajas":2064},{"periodo":"2022-12","bev":0,"phev":4,"hev":326,"otro":280,"bajas":3164},{"periodo":"2023-01","bev":0,"phev":3,"hev":254,"otro":257,"bajas":1359},{"periodo":"2023-02","bev":0,"phev":2,"hev":418,"otro":264,"bajas":1433},{"periodo":"2023-03","bev":0,"phev":7,"hev":666,"otro":456,"bajas":1890},{"periodo":"2023-04","bev":0,"phev":0,"hev":256,"otro":276,"bajas":1521},{"periodo":"2023-05","bev":0,"phev":2,"hev":594,"otro":426,"bajas":2226},{"periodo":"2023-06","bev":0,"phev":3,"hev":569,"otro":463,"bajas":1890},{"periodo":"2023-07","bev":0,"phev":0,"hev":489,"otro":393,"bajas":3496},{"periodo":"2023-08","bev":0,"phev":5,"hev":392,"otro":347,"bajas":1350},{"periodo":"2023-09","bev":0,"phev":1,"hev":478,"otro":385,"bajas":1813},{"periodo":"2023-10","bev":0,"phev":23,"hev":444,"otro":418,"bajas":1834},{"periodo":"2023-11","bev":0,"phev":11,"hev":383,"otro":367,"bajas":2001},{"periodo":"2023-12","bev":0,"phev":10,"hev":625,"otro":339,"bajas":2796},{"periodo":"2024-01","bev":0,"phev":2,"hev":344,"otro":362,"bajas":1412},{"periodo":"2024-02","bev":0,"phev":0,"hev":508,"otro":400,"bajas":14401},{"periodo":"2024-03","bev":0,"phev":2,"hev":800,"otro":437,"bajas":1464},{"periodo":"2024-04","bev":0,"phev":1,"hev":307,"otro":432,"bajas":1739},{"periodo":"2024-05","bev":0,"phev":1,"hev":442,"otro":580,"bajas":1866},{"periodo":"2024-06","bev":0,"phev":11,"hev":669,"otro":500,"bajas":1553},{"periodo":"2024-07","bev":0,"phev":1,"hev":596,"otro":472,"bajas":1669},{"periodo":"2024-08","bev":0,"phev":1,"hev":349,"otro":305,"bajas":1453},{"periodo":"2024-09","bev":0,"phev":1,"hev":620,"otro":394,"bajas":1569},{"periodo":"2024-10","bev":0,"phev":3,"hev":577,"otro":425,"bajas":2012},{"periodo":"2024-11","bev":0,"phev":1,"hev":512,"otro":434,"bajas":3030},{"periodo":"2024-12","bev":0,"phev":23,"hev":726,"otro":465,"bajas":3966},{"periodo":"2025-01","bev":0,"phev":1,"hev":415,"otro":255,"bajas":1816},{"periodo":"2025-02","bev":0,"phev":2,"hev":546,"otro":222,"bajas":1935},{"periodo":"2025-03","bev":0,"phev":6,"hev":916,"otro":263,"bajas":2081},{"periodo":"2025-04","bev":0,"phev":3,"hev":359,"otro":261,"bajas":1819},{"periodo":"2025-05","bev":0,"phev":1,"hev":461,"otro":266,"bajas":1890},{"periodo":"2025-06","bev":0,"phev":1,"hev":490,"otro":292,"bajas":1789},{"periodo":"2025-07","bev":0,"phev":1,"hev":314,"otro":301,"bajas":1961},{"periodo":"2025-08","bev":0,"phev":0,"hev":276,"otro":194,"bajas":1475},{"periodo":"2025-09","bev":0,"phev":4,"hev":486,"otro":246,"bajas":1840},{"periodo":"2025-10","bev":0,"phev":0,"hev":409,"otro":292,"bajas":2472},{"periodo":"2025-11","bev":0,"phev":2,"hev":424,"otro":229,"bajas":2113},{"periodo":"2025-12","bev":0,"phev":2,"hev":697,"otro":285,"bajas":5316},{"periodo":"2026-01","bev":0,"phev":4,"hev":343,"otro":318,"bajas":1387},{"periodo":"2026-02","bev":5,"phev":0,"hev":530,"otro":300,"bajas":1572},{"periodo":"2026-03","bev":6,"phev":0,"hev":745,"otro":451,"bajas":1814}],"mix_tipo_grupo":{"autobus":{"total":5,"bev":0,"phev":0,"hev":0,"no_enchufable":5},"camion":{"total":13,"bev":0,"phev":0,"hev":0,"no_enchufable":13},"especial":{"total":133,"bev":0,"phev":0,"hev":22,"no_enchufable":133},"furgoneta_van":{"total":128224,"bev":0,"phev":0,"hev":0,"no_enchufable":128224},"moto":{"total":378164,"bev":1,"phev":0,"hev":0,"no_enchufable":378163},"otros":{"total":10,"bev":0,"phev":0,"hev":0,"no_enchufable":10},"quad_atv":{"total":33985,"bev":0,"phev":0,"hev":0,"no_enchufable":33985},"remolque":{"total":1,"bev":0,"phev":0,"hev":0,"no_enchufable":1},"turismo":{"total":139169,"bev":11,"phev":251,"hev":28803,"no_enchufable":138907}},"top_modelos_parque":[{"modelo":"VITARA","tipo_grupo":"turismo","total":30958,"bev":0,"phev":0,"hev":10127,"no_ev":20831},{"modelo":"UH125","tipo_grupo":"moto","total":28445,"bev":0,"phev":0,"hev":0,"no_ev":28445},{"modelo":"GRAND VITARA","tipo_grupo":"furgoneta_van","total":27517,"bev":0,"phev":0,"hev":0,"no_ev":27517},{"modelo":"VITARA","tipo_grupo":"furgoneta_van","total":27027,"bev":0,"phev":0,"hev":0,"no_ev":27027},{"modelo":"SWIFT","tipo_grupo":"turismo","total":22361,"bev":0,"phev":0,"hev":5413,"no_ev":16948},{"modelo":"JIMNY","tipo_grupo":"furgoneta_van","total":13047,"bev":0,"phev":0,"hev":0,"no_ev":13047},{"modelo":"SX4","tipo_grupo":"turismo","total":12058,"bev":0,"phev":0,"hev":1084,"no_ev":10974},{"modelo":"GRAND VITARA","tipo_grupo":"turismo","total":11049,"bev":0,"phev":0,"hev":0,"no_ev":11049},{"modelo":"GSR600","tipo_grupo":"moto","total":8863,"bev":0,"phev":0,"hev":0,"no_ev":8863},{"modelo":"DL650","tipo_grupo":"moto","total":7221,"bev":0,"phev":0,"hev":0,"no_ev":7221},{"modelo":"LT Z400","tipo_grupo":"quad_atv","total":7026,"bev":0,"phev":0,"hev":0,"no_ev":7026},{"modelo":"IGNIS","tipo_grupo":"turismo","total":6995,"bev":0,"phev":1,"hev":3028,"no_ev":3966},{"modelo":"AN400","tipo_grupo":"moto","total":6772,"bev":0,"phev":0,"hev":0,"no_ev":6772},{"modelo":"UH200","tipo_grupo":"moto","total":6232,"bev":0,"phev":0,"hev":0,"no_ev":6232},{"modelo":"JIMNY","tipo_grupo":"turismo","total":6189,"bev":0,"phev":0,"hev":0,"no_ev":6189},{"modelo":"LT-Z400","tipo_grupo":"quad_atv","total":6068,"bev":0,"phev":0,"hev":0,"no_ev":6068},{"modelo":"SAMURAI","tipo_grupo":"furgoneta_van","total":5157,"bev":0,"phev":0,"hev":0,"no_ev":5157},{"modelo":"RV125","tipo_grupo":"moto","total":3101,"bev":0,"phev":0,"hev":0,"no_ev":3101},{"modelo":"S-CROSS","tipo_grupo":"turismo","total":2941,"bev":0,"phev":0,"hev":2940,"no_ev":1},{"modelo":"AN250","tipo_grupo":"moto","total":2882,"bev":0,"phev":0,"hev":0,"no_ev":2882}],"mix_tecnologia_anual":[{"año":2014,"bev":0,"phev":0,"hev":0,"otro":648},{"año":2015,"bev":0,"phev":0,"hev":0,"otro":12567},{"año":2016,"bev":0,"phev":0,"hev":0,"otro":14228},{"año":2017,"bev":0,"phev":0,"hev":249,"otro":12892},{"año":2018,"bev":0,"phev":0,"hev":468,"otro":13327},{"año":2019,"bev":0,"phev":0,"hev":706,"otro":14160},{"año":2020,"bev":0,"phev":80,"hev":3390,"otro":5553},{"año":2021,"bev":0,"phev":30,"hev":5034,"otro":3638},{"año":2022,"bev":0,"phev":26,"hev":3531,"otro":3282},{"año":2023,"bev":0,"phev":67,"hev":5568,"otro":4391},{"año":2024,"bev":0,"phev":47,"hev":6450,"otro":5206},{"año":2025,"bev":0,"phev":23,"hev":5793,"otro":3106},{"año":2026,"bev":11,"phev":4,"hev":1618,"otro":1069}],"por_provincia":{"10":{"parque":7654,"cuota_pct":2.128,"ranking":15,"top_3":["VITARA","GRAND VITARA","JIMNY"]},"11":{"parque":17471,"cuota_pct":1.781,"ranking":20,"top_3":["VITARA","GRAND VITARA","SWIFT"]},"12":{"parque":7740,"cuota_pct":1.521,"ranking":19,"top_3":["VITARA","GRAND VITARA","SWIFT"]},"13":{"parque":7400,"cuota_pct":1.739,"ranking":16,"top_3":["VITARA","GRAND VITARA","LT Z400"]},"14":{"parque":17654,"cuota_pct":2.735,"ranking":13,"top_3":["VITARA","GRAND VITARA","UH125"]},"15":{"parque":14233,"cuota_pct":1.616,"ranking":17,"top_3":["GRAND VITARA","SWIFT","VITARA"]},"16":{"parque":5371,"cuota_pct":2.658,"ranking":12,"top_3":["GRAND VITARA","VITARA","SX4"]},"17":{"parque":14372,"cuota_pct":1.958,"ranking":17,"top_3":["VITARA","JIMNY","GRAND VITARA"]},"18":{"parque":16582,"cuota_pct":1.984,"ranking":17,"top_3":["VITARA","GRAND VITARA","JIMNY"]},"19":{"parque":5319,"cuota_pct":2.219,"ranking":15,"top_3":["VITARA","GRAND VITARA","JIMNY"]},"20":{"parque":8560,"cuota_pct":1.681,"ranking":18,"top_3":["VITARA","GRAND VITARA","UH125"]},"21":{"parque":7212,"cuota_pct":1.706,"ranking":18,"top_3":["VITARA","GRAND VITARA","SWIFT"]},"22":{"parque":4330,"cuota_pct":2.068,"ranking":14,"top_3":["VITARA","GRAND VITARA","JIMNY"]},"23":{"parque":16333,"cuota_pct":3.032,"ranking":12,"top_3":["VITARA","GRAND VITARA","JIMNY"]},"24":{"parque":10651,"cuota_pct":2.616,"ranking":13,"top_3":["VITARA","GRAND VITARA","JIMNY"]},"25":{"parque":6281,"cuota_pct":1.588,"ranking":18,"top_3":["VITARA","GRAND VITARA","JIMNY"]},"26":{"parque":4891,"cuota_pct":2.006,"ranking":15,"top_3":["VITARA","GRAND VITARA","SX4"]},"27":{"parque":8557,"cuota_pct":2.708,"ranking":13,"top_3":["GRAND VITARA","VITARA","JIMNY"]},"28":{"parque":58688,"cuota_pct":1.033,"ranking":22,"top_3":["VITARA","SWIFT","UH125"]},"29":{"parque":27688,"cuota_pct":1.848,"ranking":19,"top_3":["VITARA","GRAND VITARA","SWIFT"]},"30":{"parque":26377,"cuota_pct":2.018,"ranking":17,"top_3":["VITARA","UH125","GRAND VITARA"]},"31":{"parque":9310,"cuota_pct":1.786,"ranking":16,"top_3":["VITARA","GRAND VITARA","JIMNY"]},"32":{"parque":5944,"cuota_pct":2.107,"ranking":13,"top_3":["VITARA","GRAND VITARA","JIMNY"]},"33":{"parque":21610,"cuota_pct":2.846,"ranking":13,"top_3":["VITARA","JIMNY","GRAND VITARA"]},"34":{"parque":2496,"cuota_pct":1.826,"ranking":13,"top_3":["VITARA","GRAND VITARA","JIMNY"]},"35":{"parque":14913,"cuota_pct":1.46,"ranking":19,"top_3":["VITARA","GRAND VITARA","SWIFT"]},"36":{"parque":16725,"cuota_pct":2.071,"ranking":15,"top_3":["UH125","VITARA","SWIFT"]},"37":{"parque":4374,"cuota_pct":1.663,"ranking":17,"top_3":["VITARA","GRAND VITARA","UH125"]},"38":{"parque":14785,"cuota_pct":1.53,"ranking":19,"top_3":["VITARA","JIMNY","GRAND VITARA"]},"39":{"parque":9247,"cuota_pct":1.913,"ranking":16,"top_3":["VITARA","UH125","GRAND VITARA"]},"40":{"parque":2530,"cuota_pct":1.724,"ranking":15,"top_3":["VITARA","GRAND VITARA","JIMNY"]},"41":{"parque":24068,"cuota_pct":1.597,"ranking":21,"top_3":["VITARA","GRAND VITARA","UH125"]},"42":{"parque":1674,"cuota_pct":2.029,"ranking":14,"top_3":["VITARA","GRAND VITARA","JIMNY"]},"43":{"parque":13890,"cuota_pct":1.976,"ranking":19,"top_3":["VITARA","GRAND VITARA","SWIFT"]},"44":{"parque":3037,"cuota_pct":2.246,"ranking":13,"top_3":["VITARA","GRAND VITARA","JIMNY"]},"45":{"parque":10148,"cuota_pct":1.536,"ranking":17,"top_3":["VITARA","GRAND VITARA","LT Z400"]},"46":{"parque":29286,"cuota_pct":1.462,"ranking":20,"top_3":["UH125","VITARA","SWIFT"]},"47":{"parque":5829,"cuota_pct":1.508,"ranking":18,"top_3":["VITARA","UH125","SWIFT"]},"48":{"parque":11268,"cuota_pct":1.534,"ranking":18,"top_3":["VITARA","GRAND VITARA","UH125"]},"49":{"parque":3185,"cuota_pct":1.998,"ranking":15,"top_3":["VITARA","GRAND VITARA","LT-Z400"]},"50":{"parque":11587,"cuota_pct":1.737,"ranking":16,"top_3":["VITARA","GRAND VITARA","UH125"]},"51":{"parque":1482,"cuota_pct":2.182,"ranking":18,"top_3":["GRAND VITARA","SWIFT","UH125"]},"52":{"parque":998,"cuota_pct":1.353,"ranking":20,"top_3":["GRAND VITARA","SWIFT","LT-Z400"]},"01":{"parque":3934,"cuota_pct":1.701,"ranking":17,"top_3":["VITARA","GRAND VITARA","SX4"]},"02":{"parque":7670,"cuota_pct":2.282,"ranking":14,"top_3":["VITARA","GRAND VITARA","UH125"]},"03":{"parque":28913,"cuota_pct":1.756,"ranking":19,"top_3":["UH125","VITARA","SWIFT"]},"04":{"parque":11414,"cuota_pct":1.755,"ranking":17,"top_3":["VITARA","GRAND VITARA","LT Z400"]},"05":{"parque":3186,"cuota_pct":2.133,"ranking":14,"top_3":["VITARA","GRAND VITARA","JIMNY"]},"06":{"parque":13067,"cuota_pct":2.14,"ranking":15,"top_3":["VITARA","GRAND VITARA","LT-Z400"]},"07":{"parque":23070,"cuota_pct":1.9,"ranking":20,"top_3":["UH125","VITARA","SWIFT"]},"08":{"parque":71558,"cuota_pct":1.834,"ranking":18,"top_3":["UH125","VITARA","SWIFT"]},"09":{"parque":5142,"cuota_pct":1.755,"ranking":16,"top_3":["VITARA","GRAND VITARA","JIMNY"]}},"sociologia":{"persona":{"D":12983,"X":5437},"renting":{"S":496,"N":17924},"servicio":{"B00":16101,"A01":1714,"A02":492,"A03":59,"B22":20,"A00":15,"A13":11,"B18":5,"A04":2,"A16":1}},"distintivo_ambiental":{"CERO":313,"ECO":29088,"C":0,"B":0,"SIN":650303},"piramide_edad":[{"años":0,"bev":11,"phev":4,"hev":1379,"no_ev":698},{"años":1,"bev":0,"phev":14,"hev":4828,"no_ev":1944},{"años":2,"bev":0,"phev":42,"hev":5931,"no_ev":3898},{"años":3,"bev":0,"phev":66,"hev":5326,"no_ev":3203},{"años":4,"bev":0,"phev":27,"hev":3273,"no_ev":2405},{"años":5,"bev":0,"phev":24,"hev":3976,"no_ev":2762},{"años":6,"bev":0,"phev":74,"hev":2773,"no_ev":4524},{"años":7,"bev":0,"phev":0,"hev":668,"no_ev":11144},{"años":8,"bev":0,"phev":0,"hev":438,"no_ev":10901},{"años":9,"bev":0,"phev":0,"hev":221,"no_ev":10986},{"años":10,"bev":0,"phev":0,"hev":10,"no_ev":11949},{"años":11,"bev":0,"phev":0,"hev":1,"no_ev":10646},{"años":12,"bev":0,"phev":0,"hev":0,"no_ev":7842},{"años":13,"bev":0,"phev":0,"hev":1,"no_ev":7627},{"años":14,"bev":0,"phev":0,"hev":0,"no_ev":10804},{"años":15,"bev":0,"phev":0,"hev":0,"no_ev":15878},{"años":16,"bev":0,"phev":0,"hev":0,"no_ev":21024},{"años":17,"bev":0,"phev":0,"hev":0,"no_ev":21754},{"años":18,"bev":0,"phev":0,"hev":0,"no_ev":37804},{"años":19,"bev":0,"phev":0,"hev":0,"no_ev":58762},{"años":20,"bev":0,"phev":0,"hev":0,"no_ev":56624},{"años":21,"bev":0,"phev":0,"hev":0,"no_ev":46870},{"años":22,"bev":0,"phev":0,"hev":0,"no_ev":32904},{"años":23,"bev":0,"phev":0,"hev":0,"no_ev":22403},{"años":24,"bev":0,"phev":0,"hev":0,"no_ev":22695},{"años":25,"bev":0,"phev":0,"hev":0,"no_ev":30428},{"años":26,"bev":0,"phev":0,"hev":0,"no_ev":40041},{"años":27,"bev":1,"phev":0,"hev":0,"no_ev":26691},{"años":28,"bev":0,"phev":0,"hev":0,"no_ev":12100},{"años":29,"bev":0,"phev":0,"hev":0,"no_ev":8873},{"años":30,"bev":0,"phev":0,"hev":0,"no_ev":6870},{"años":31,"bev":0,"phev":0,"hev":0,"no_ev":5787},{"años":32,"bev":0,"phev":0,"hev":0,"no_ev":5686},{"años":33,"bev":0,"phev":0,"hev":0,"no_ev":7248},{"años":34,"bev":0,"phev":0,"hev":0,"no_ev":11506},{"años":35,"bev":0,"phev":0,"hev":0,"no_ev":14266},{"años":36,"bev":0,"phev":0,"hev":0,"no_ev":11588},{"años":37,"bev":0,"phev":0,"hev":0,"no_ev":9347},{"años":38,"bev":0,"phev":0,"hev":0,"no_ev":7079},{"años":39,"bev":0,"phev":0,"hev":0,"no_ev":5342},{"años":40,"bev":0,"phev":0,"hev":0,"no_ev":4255},{"años":41,"bev":0,"phev":0,"hev":0,"no_ev":2916},{"años":42,"bev":0,"phev":0,"hev":0,"no_ev":246},{"años":43,"bev":0,"phev":0,"hev":0,"no_ev":319},{"años":44,"bev":0,"phev":0,"hev":0,"no_ev":336},{"años":45,"bev":0,"phev":0,"hev":0,"no_ev":185},{"años":46,"bev":0,"phev":0,"hev":0,"no_ev":173},{"años":47,"bev":0,"phev":0,"hev":0,"no_ev":146},{"años":48,"bev":0,"phev":0,"hev":0,"no_ev":196},{"años":49,"bev":0,"phev":0,"hev":0,"no_ev":216},{"años":50,"bev":0,"phev":0,"hev":0,"no_ev":229},{"años":51,"bev":0,"phev":0,"hev":0,"no_ev":224},{"años":52,"bev":0,"phev":0,"hev":0,"no_ev":200},{"años":53,"bev":0,"phev":0,"hev":0,"no_ev":41},{"años":54,"bev":0,"phev":0,"hev":0,"no_ev":15},{"años":56,"bev":0,"phev":0,"hev":0,"no_ev":1},{"años":57,"bev":0,"phev":0,"hev":0,"no_ev":3},{"años":58,"bev":0,"phev":0,"hev":0,"no_ev":2},{"años":60,"bev":0,"phev":0,"hev":0,"no_ev":1},{"años":61,"bev":0,"phev":0,"hev":0,"no_ev":1},{"años":62,"bev":0,"phev":0,"hev":0,"no_ev":1},{"años":63,"bev":0,"phev":0,"hev":0,"no_ev":2},{"años":65,"bev":0,"phev":0,"hev":0,"no_ev":3}],"radar_vs_mercado":{"co2_marca":116.3,"kw_marca":15.5,"peso_marca":1234,"autonomia_bev_km_marca":null,"n_muestra_marca":11996,"co2_mercado":117.6,"kw_mercado":100.8,"peso_mercado":1505,"autonomia_bev_km_mercado":467}}